Metadata-Version: 2.0
Name: django-states2
Version: 1.6.10
Summary: State machine for django models
Home-page: https://github.com/vikingco/django-states2
Author: Jonathan Slenders, Gert van Gool, Maarten Timmerman, Steven (rh0dium), Unleashed NV
Author-email: operations@unleashed.be
License: BSD
Platform: UNKNOWN
Classifier: Intended Audience :: Developers
Classifier: Programming Language :: Python
Classifier: Operating System :: OS Independent
Classifier: Environment :: Web Environment
Classifier: Framework :: Django
